LICENSE
MANIFEST.in
README.md
setup.cfg
setup.py
tap_fullstory/__init__.py
tap_fullstory.egg-info/PKG-INFO
tap_fullstory.egg-info/SOURCES.txt
tap_fullstory.egg-info/dependency_links.txt
tap_fullstory.egg-info/entry_points.txt
tap_fullstory.egg-info/requires.txt
tap_fullstory.egg-info/top_level.txt
tap_fullstory/schemas/events.json