Metadata-Version: 1.1
Name: tap-fullstory
Version: 0.1.2
Summary: Singer.io tap for extracting data from the FullStory API
Home-page: http://singer.io
Author: Stitch
Author-email: UNKNOWN
License: UNKNOWN
Platform: UNKNOWN
Classifier: Programming Language :: Python :: 3 :: Only
